helios/__init__.py
helios/cli_parser.py
helios/config.py
helios/constants.py
helios/dev_tools.py
helios/events.py
helios/exceptions.py
helios/helios_config.py
helios/helios_config_template.py
helios/main.py
helios/server.py
helios/chains/__init__.py
helios/chains/base.py
helios/chains/coro.py
helios/chains/header.py
helios/chains/light.py
helios/chains/mainnet.py
helios/chains/ropsten.py
helios/db/__init__.py
helios/db/base.py
helios/db/chain.py
helios/db/chain_head.py
helios/db/consensus.py
helios/db/header.py
helios/extensibility/__init__.py
helios/extensibility/events.py
helios/extensibility/exceptions.py
helios/extensibility/plugin.py
helios/extensibility/plugin_manager.py
helios/nodes/__init__.py
helios/nodes/base.py
helios/nodes/full.py
helios/nodes/light.py
helios/nodes/mainnet.py
helios/nodes/ropsten.py
helios/p2p/__init__.py
helios/p2p/handlers.py
helios/plugins/__init__.py
helios/plugins/registry.py
helios/plugins/builtin/__init__.py
helios/plugins/builtin/attach/__init__.py
helios/plugins/builtin/attach/console.py
helios/plugins/builtin/attach/plugin.py
helios/plugins/builtin/ethstats/__init__.py
helios/plugins/builtin/ethstats/ethstats_client.py
helios/plugins/builtin/ethstats/ethstats_service.py
helios/plugins/builtin/ethstats/plugin.py
helios/plugins/builtin/fix_unclean_shutdown/__init__.py
helios/plugins/builtin/fix_unclean_shutdown/plugin.py
helios/plugins/builtin/json_rpc/__init__.py
helios/plugins/builtin/json_rpc/plugin.py
helios/plugins/builtin/json_rpc/websocket_server.py
helios/plugins/builtin/light_peer_chain_bridge/__init__.py
helios/plugins/builtin/light_peer_chain_bridge/light_peer_chain_bridge.py
helios/plugins/builtin/light_peer_chain_bridge/plugin.py
helios/plugins/builtin/rpc_http_proxy/__init__.py
helios/plugins/builtin/rpc_http_proxy/plugin.py
helios/plugins/builtin/rpc_websocket_proxy/__init__.py
helios/plugins/builtin/rpc_websocket_proxy/plugin.py
helios/plugins/builtin/rpc_websocket_proxy/websocket_proxy_server.py
py_helios_node-0.3.0.dist-info/LICENSE
py_helios_node-0.3.0.dist-info/METADATA
py_helios_node-0.3.0.dist-info/WHEEL
py_helios_node-0.3.0.dist-info/entry_points.txt
py_helios_node-0.3.0.dist-info/top_level.txt
py_helios_node-0.3.0.dist-info/RECORD
